MANIFEST.in
README.md
setup.py
django_lightpdf.egg-info/PKG-INFO
django_lightpdf.egg-info/SOURCES.txt
django_lightpdf.egg-info/dependency_links.txt
django_lightpdf.egg-info/pbr.json
django_lightpdf.egg-info/requires.txt
django_lightpdf.egg-info/top_level.txt
lightpdf/__init__.py
lightpdf/mixins.py
lightpdf/settings.py
lightpdf/tests.py