Metadata-Version: 1.1
Name: django-lightpdf
Version: 0.1.1
Summary: A simple Django app to help generate pdfs
Home-page: https://github.com/claudiutopriceanu/django-lightpdf
Author: Claudiu Topriceanu
Author-email: ctopriceanu@example.com
License: MIT License
Platform: UNKNOWN
Classifier: Environment :: Web Environment
Classifier: Framework :: Django
Classifier: Framework :: Django :: 1.9
Classifier: Intended Audience :: Developers
Classifier: License :: OSI Approved :: BSD License
Classifier: Operating System :: OS Independent
Classifier: Programming Language :: Python
Classifier: Programming Language :: Python :: 2.7
Classifier: Topic :: Internet :: WWW/HTTP
Classifier: Topic :: Internet :: WWW/HTTP :: Dynamic Content
